scVital/__benchmarking.py
scVital/__init__.py
scVital/__plotting.py
scVital/lss.py
scVital/merging.py
scVital/scVital.py
scvital-1.0.0.dist-info/METADATA
scvital-1.0.0.dist-info/WHEEL
scvital-1.0.0.dist-info/licenses/LICENSE
scvital-1.0.0.dist-info/RECORD
