Metadata-Version: 2.4
Name: scVital
Version: 1.0.0
Summary: Deep Learning Algorithm for cross-species integration of scRNA-seq data
Project-URL: Homepage, https://github.com/j-rub/scVital
Author-email: Jonathan Rub <jor4008@medDOTcornell.edu>
License:                     GNU GENERAL PUBLIC LICENSE
License-File: LICENSE
Classifier: Intended Audience :: Science/Research
Classifier: License :: OSI Approved :: GNU General Public License v3 or later (GPLv3+)
Classifier: Operating System :: OS Independent
Classifier: Programming Language :: Python :: 3
Classifier: Topic :: Scientific/Engineering :: Bio-Informatics
Requires-Python: >=3.8
Requires-Dist: matplotlib
Requires-Dist: networkx
Requires-Dist: numpy
Requires-Dist: pandas
Requires-Dist: scanpy
Requires-Dist: scikit-learn
Requires-Dist: scipy
Requires-Dist: torch
